{"__symbolic":"module","version":4,"metadata":{"SyComponentsService":{"__symbolic":"class","decorators":[{"__symbolic":"call","expression":{"__symbolic":"reference","module":"@angular/core","name":"Injectable","line":2,"character":1},"arguments":[{"providedIn":"root"}]}],"members":{"__ctor__":[{"__symbolic":"constructor"}]},"statics":{"ngInjectableDef":{}}},"SyComponentsComponent":{"__symbolic":"class","decorators":[{"__symbolic":"call","expression":{"__symbolic":"reference","module":"@angular/core","name":"Component","line":2,"character":1},"arguments":[{"selector":"lib-sy-components","template":"\n    <p>\n      sy-components works!\n    </p>\n  ","styles":[]}]}],"members":{"__ctor__":[{"__symbolic":"constructor"}],"ngOnInit":[{"__symbolic":"method"}]}},"SyComponentsModule":{"__symbolic":"class","decorators":[{"__symbolic":"call","expression":{"__symbolic":"reference","module":"@angular/core","name":"NgModule","line":16,"character":1},"arguments":[{"declarations":[{"__symbolic":"reference","name":"SyComponentsComponent"},{"__symbolic":"reference","name":"ɵa"},{"__symbolic":"reference","name":"ɵb"},{"__symbolic":"reference","name":"ɵc"}],"imports":[{"__symbolic":"reference","module":"@angular/forms","name":"FormsModule","line":22,"character":4},{"__symbolic":"reference","module":"@angular/common","name":"CommonModule","line":23,"character":4},{"__symbolic":"reference","module":"@fortawesome/angular-fontawesome","name":"FontAwesomeModule","line":24,"character":4},{"__symbolic":"reference","module":"@angular/common/http","name":"HttpClientModule","line":25,"character":4},{"__symbolic":"reference","module":"@angular/router","name":"RouterModule","line":26,"character":4}],"exports":[{"__symbolic":"reference","name":"SyComponentsComponent"},{"__symbolic":"reference","name":"ɵa"},{"__symbolic":"reference","name":"ɵe"},{"__symbolic":"reference","name":"ɵw"},{"__symbolic":"reference","name":"ɵb"}]}]}],"members":{"__ctor__":[{"__symbolic":"constructor"}]}},"ɵa":{"__symbolic":"class","decorators":[{"__symbolic":"call","expression":{"__symbolic":"reference","module":"@angular/core","name":"Component","line":3,"character":1},"arguments":[{"selector":"sy-history","template":"<span aria-hidden=\"true\">\n    <fa-icon [icon]=\"['fas', 'minus']\" size=\"sm\"></fa-icon>\n</span>\n<ul>\n  <li *ngFor=\"let item of data; let i = index;\" [ngClass]=\"'history-item-'+i\"\n    [class.current]=\"item.id && item.id == currentId\"\n    [attr.aria-label]=\" item.id == currentId && item.ariaLabel ? item.ariaLabel : '' \">\n    <span>\n      <strong>{{item.date}}</strong>\n      <a *ngIf=\"item.url && item.title\" [routerLink]='item.url.split(\"/\")'\n       [queryParams]=\"item.queryParams\"\n        [attr.id]=\"id ? (id + i) : undefined\">{{ item.title }}</a>\n      <ng-container *ngIf=\"!item.url && item.title\">{{ item.title }}</ng-container>\n      <br *ngIf=\"item.title && item.description\" />\n      <p *ngIf=\"item.description\" [innerHTML]=\"item.description\"></p>\n    </span>\n  </li>\n</ul>\n\n<span aria-hidden=\"true\">\n    <fa-icon [icon]=\"['fas', 'minus']\" size=\"sm\"></fa-icon>\n</span>","styles":["fa-icon{color:#ccc;padding-left:4px}ul{list-style-type:none;padding-left:10px;margin:-10px 0}ul li{margin:0 0 0 -8px;padding:15px 0;border-left:2px solid #ccc;content:\"\\F111\";font:17px/1 FontAwesome;color:#5b616b;background-color:#fff}ul span{display:inline-table;margin-left:4px;width:90%}ul span em{padding-left:5px;display:block}ul span strong{display:block}ul .fa{font-size:12px;color:#fdb81e;padding-left:5px}"]}]}],"members":{"id":[{"__symbolic":"property","decorators":[{"__symbolic":"call","expression":{"__symbolic":"reference","module":"@angular/core","name":"Input","line":12,"character":3}}]}],"data":[{"__symbolic":"property","decorators":[{"__symbolic":"call","expression":{"__symbolic":"reference","module":"@angular/core","name":"Input","line":16,"character":3}}]}],"currentId":[{"__symbolic":"property","decorators":[{"__symbolic":"call","expression":{"__symbolic":"reference","module":"@angular/core","name":"Input","line":20,"character":3}}]}]}},"ɵb":{"__symbolic":"class","decorators":[{"__symbolic":"call","expression":{"__symbolic":"reference","module":"@angular/core","name":"Component","line":22,"character":1},"arguments":[{"selector":"sy-listbox","providers":[{"provide":{"__symbolic":"reference","module":"@angular/forms","name":"NG_VALUE_ACCESSOR","line":27,"character":13},"useExisting":{"__symbolic":"reference","name":"ɵb"},"multi":true}],"template":"<div class=\"listbox-width\">\r\n    <ng-container *ngTemplateOutlet=\"listTemplate\"></ng-container>\r\n</div>\r\n\r\n<ng-template #listTemplate>\r\n    <sy-fieldset-wrapper [label]=\"label\" [hint]=\"hint\" [errorMessage]=\"errorMessage\" [required]=\"required\">\r\n        <div id=\"listboxgroup-lable\" (keydown)=\"onKeyDown($event)\">\r\n            <ul role=\"listboxgroup\" tabindex=\"0\" aria-labelledby=\"listboxgroup-lable\" #checkboxList class=\"usa-unstyled-list checkbox-container\">\r\n\r\n                <li (mouseenter)=\"onHover(i)\" [class]=\"option['highlighted']? 'selected-item':''\" *ngFor=\"let option of options; let i = index;\" role=\"option\" aria-checked=\"false\">\r\n\r\n                    <input [disabled]=\"option.disabled || disabled?'disabled':null \" [attr.id]=\"option.name\" [attr.value]=\"option.value\" [attr.type]=\"optionsMode\" [attr.aria-label]=\"option.name\" [required]=\"option.required\" [checked]=\"option.checked\" name=\"option\" (change)=\"onChecked($event,option)\">\r\n                    <label [attr.for]=\"option.name\">{{option.label}}</label>\r\n                </li>\r\n            </ul>\r\n            <ul #srOnly class=\"usa-sr-only\" aria-live=\"assertive\" aria-relevant=\"additions\"></ul>\r\n        </div>\r\n    </sy-fieldset-wrapper>\r\n</ng-template>","styles":[".checkbox-container{position:relative;height:130px;max-height:145px;overflow-y:scroll;overflow-x:hidden;margin:10px;padding-left:10px}.selected-item{background-color:#0071bc;color:#fff}.listbox-width{max-width:500px}"]}]}],"members":{"model":[{"__symbolic":"property","decorators":[{"__symbolic":"call","expression":{"__symbolic":"reference","module":"@angular/core","name":"Input","line":36,"character":2}}]}],"options":[{"__symbolic":"property","decorators":[{"__symbolic":"call","expression":{"__symbolic":"reference","module":"@angular/core","name":"Input","line":40,"character":2}}]}],"label":[{"__symbolic":"property","decorators":[{"__symbolic":"call","expression":{"__symbolic":"reference","module":"@angular/core","name":"Input","line":44,"character":2}}]}],"name":[{"__symbolic":"property","decorators":[{"__symbolic":"call","expression":{"__symbolic":"reference","module":"@angular/core","name":"Input","line":48,"character":2}}]}],"hint":[{"__symbolic":"property","decorators":[{"__symbolic":"call","expression":{"__symbolic":"reference","module":"@angular/core","name":"Input","line":52,"character":2}}]}],"required":[{"__symbolic":"property","decorators":[{"__symbolic":"call","expression":{"__symbolic":"reference","module":"@angular/core","name":"Input","line":56,"character":2}}]}],"errorMessage":[{"__symbolic":"property","decorators":[{"__symbolic":"call","expression":{"__symbolic":"reference","module":"@angular/core","name":"Input","line":60,"character":2}}]}],"control":[{"__symbolic":"property","decorators":[{"__symbolic":"call","expression":{"__symbolic":"reference","module":"@angular/core","name":"Input","line":64,"character":2}}]}],"id":[{"__symbolic":"property","decorators":[{"__symbolic":"call","expression":{"__symbolic":"reference","module":"@angular/core","name":"Input","line":69,"character":2}}]}],"srOnly":[{"__symbolic":"property","decorators":[{"__symbolic":"call","expression":{"__symbolic":"reference","module":"@angular/core","name":"ViewChild","line":76,"character":2},"arguments":["srOnly"]}]}],"checkboxListElement":[{"__symbolic":"property","decorators":[{"__symbolic":"call","expression":{"__symbolic":"reference","module":"@angular/core","name":"ViewChild","line":81,"character":2},"arguments":["checkboxList"]}]}],"isSingleMode":[{"__symbolic":"property","decorators":[{"__symbolic":"call","expression":{"__symbolic":"reference","module":"@angular/core","name":"Input","line":86,"character":2}}]}],"modelChange":[{"__symbolic":"property","decorators":[{"__symbolic":"call","expression":{"__symbolic":"reference","module":"@angular/core","name":"Output","line":103,"character":2}}]}],"optionSelected":[{"__symbolic":"property","decorators":[{"__symbolic":"call","expression":{"__symbolic":"reference","module":"@angular/core","name":"Output","line":105,"character":2}}]}],"wrapper":[{"__symbolic":"property","decorators":[{"__symbolic":"call","expression":{"__symbolic":"reference","module":"@angular/core","name":"ViewChild","line":107,"character":2},"arguments":[{"__symbolic":"reference","name":"ɵc"}]}]}],"ngOnInit":[{"__symbolic":"method"}],"setSelectedItem":[{"__symbolic":"method"}],"isChecked":[{"__symbolic":"method"}],"onHover":[{"__symbolic":"method"}],"setHighlightedItem":[{"__symbolic":"method"}],"addScreenReaderMessage":[{"__symbolic":"method"}],"setfocus":[{"__symbolic":"method"}],"onChecked":[{"__symbolic":"method"}],"onKeyDown":[{"__symbolic":"method"}],"emitModel":[{"__symbolic":"method"}],"registerOnChange":[{"__symbolic":"method"}],"registerOnTouched":[{"__symbolic":"method"}],"setDisabledState":[{"__symbolic":"method"}],"writeValue":[{"__symbolic":"method"}]}},"ɵc":{"__symbolic":"class","decorators":[{"__symbolic":"call","expression":{"__symbolic":"reference","module":"@angular/core","name":"Component","line":9,"character":1},"arguments":[{"selector":"sy-fieldset-wrapper","template":"<div [class.sy-input-error]=\"displayErrors()\">\r\n\r\n    <fieldset class=\"fieldset\">\r\n\r\n        <legend *ngIf=\"label || required\" [class.required-text]=\"displayErrors()\">\r\n            {{label}}\r\n            <span *ngIf=\"required\" class=\"required-text\">\r\n        Required\r\n      </span>\r\n            <ng-content select=\"[label-right]\"></ng-content>\r\n        </legend>\r\n\r\n        <div #hintContainer *ngIf=\"hint\" class=\"sy-form-hint\" aria-live=\"polite\" [innerHTML]=\"hint\" [style.overflow]=\"setOverflow()\" [style.height]=\"setHeight()\">\r\n        </div>\r\n\r\n        <div *ngIf=\"showToggle\" class=\"toggle-more\">\r\n            <a href=\"javascript:void(0)\" (click)=\"toggleHint(toggleOpen)\">\r\n        {{ toggleOpen?\"less\":\"more\"}}\r\n      </a>\r\n        </div>\r\n\r\n        <span *ngIf=\"displayErrors()\" class=\"usa-input-error-message\" aria-live=\"assertive\">\r\n      <ng-container *ngIf=\"displayErrorList() else single\">\r\n        <ul>\r\n          <li *ngFor=\"let msg of errorMessages\">\r\n            {{ msg }}\r\n          </li>\r\n        </ul>\r\n      </ng-container>\r\n      <ng-template #single>\r\n        {{ errorMessages[0] }}\r\n      </ng-template>\r\n    </span>\r\n\r\n        <ng-content></ng-content>\r\n\r\n    </fieldset>\r\n\r\n</div>","styles":[".checkbox-container{position:relative;height:130px;max-height:145px;overflow-y:scroll;overflow-x:hidden;margin:10px;padding-left:10px}.selected-item{background-color:#0071bc;color:#fff}.required-text{color:red}.sy-form-hint{font-size:14px}.sy-input-error{color:red}fieldset{border:none}"]}]}],"members":{"label":[{"__symbolic":"property","decorators":[{"__symbolic":"call","expression":{"__symbolic":"reference","module":"@angular/core","name":"Input","line":18,"character":3}}]}],"hint":[{"__symbolic":"property","decorators":[{"__symbolic":"call","expression":{"__symbolic":"reference","module":"@angular/core","name":"Input","line":22,"character":3}}]}],"errorMessages":[{"__symbolic":"property","decorators":[{"__symbolic":"call","expression":{"__symbolic":"reference","module":"@angular/core","name":"Input","line":26,"character":3}}]}],"errorMessage":[{"__symbolic":"property","decorators":[{"__symbolic":"call","expression":{"__symbolic":"reference","module":"@angular/core","name":"Input","line":30,"character":3}}]}],"required":[{"__symbolic":"property","decorators":[{"__symbolic":"call","expression":{"__symbolic":"reference","module":"@angular/core","name":"Input","line":45,"character":3}}]}],"hintContainer":[{"__symbolic":"property","decorators":[{"__symbolic":"call","expression":{"__symbolic":"reference","module":"@angular/core","name":"ViewChild","line":46,"character":3},"arguments":["hintContainer"]}]}],"__ctor__":[{"__symbolic":"constructor","parameters":[{"__symbolic":"reference","module":"@angular/core","name":"ChangeDetectorRef","line":53,"character":27}]}],"ngOnChanges":[{"__symbolic":"method"}],"ngAfterViewInit":[{"__symbolic":"method"}],"ngAfterViewChecked":[{"__symbolic":"method"}],"calcToggle":[{"__symbolic":"method"}],"onResize":[{"__symbolic":"method","decorators":[{"__symbolic":"call","expression":{"__symbolic":"reference","module":"@angular/core","name":"HostListener","line":92,"character":3},"arguments":["window:resize",["$event"]]}]}],"toggleHint":[{"__symbolic":"method"}],"calculateNumberOfLines":[{"__symbolic":"method"}],"formatErrors":[{"__symbolic":"method"}],"clearError":[{"__symbolic":"method"}],"displayErrors":[{"__symbolic":"method"}],"displayErrorList":[{"__symbolic":"method"}],"setOverflow":[{"__symbolic":"method"}],"setHeight":[{"__symbolic":"method"}],"_formatError":[{"__symbolic":"method"}],"formatInvalidErrors":[{"__symbolic":"method"}],"setInvalidError":[{"__symbolic":"method"}]}},"ɵd":[{"__symbolic":"reference","name":"ɵf"},{"__symbolic":"reference","name":"ɵg"},{"__symbolic":"reference","name":"ɵh"},{"__symbolic":"reference","name":"ɵi"},{"__symbolic":"reference","name":"ɵj"},{"__symbolic":"reference","name":"ɵl"},{"__symbolic":"reference","name":"ɵm"},{"__symbolic":"reference","name":"ɵn"},{"__symbolic":"reference","name":"ɵo"},{"__symbolic":"reference","name":"ɵp"},{"__symbolic":"reference","name":"ɵq"},{"__symbolic":"reference","name":"ɵr"},{"__symbolic":"reference","name":"ɵs"},{"__symbolic":"reference","name":"ɵt"},{"__symbolic":"reference","name":"ɵu"},{"__symbolic":"reference","name":"ɵv"}],"ɵe":{"__symbolic":"class","decorators":[{"__symbolic":"call","expression":{"__symbolic":"reference","module":"@angular/core","name":"NgModule","line":41,"character":1},"arguments":[{"imports":[{"__symbolic":"reference","module":"@angular/common","name":"CommonModule","line":43,"character":8},{"__symbolic":"reference","module":"@angular/forms","name":"FormsModule","line":44,"character":8},{"__symbolic":"reference","module":"@fortawesome/angular-fontawesome","name":"FontAwesomeModule","line":45,"character":8},{"__symbolic":"reference","module":"@angular/forms","name":"ReactiveFormsModule","line":46,"character":8}],"declarations":[{"__symbolic":"spread","expression":{"__symbolic":"reference","name":"ɵd"}}],"exports":[{"__symbolic":"spread","expression":{"__symbolic":"reference","name":"ɵd"}}],"providers":[{"__symbolic":"reference","name":"ɵk"}]}]}],"members":{}},"ɵf":{"__symbolic":"class","decorators":[{"__symbolic":"call","expression":{"__symbolic":"reference","module":"@angular/core","name":"Component","line":3,"character":1},"arguments":[{"selector":"sy-audit-trail","template":"<div class=\"audit-trail\">\n  <div>\n    <label>Last Modified :</label>\n    <label> {{lastModified  | date : dateFormat }}</label>\n  </div>\n  <div>\n    <label>Last Modified By :</label>\n    <label>\n      <a href=\"mailto:{{lastModifiedByEmail}}\">{{lastModifiedByEmail}}</a>\n    </label>\n  </div>\n  <div>\n    <label>Created :</label>\n    <label>{{created |  date : dateFormat}}</label>\n  </div>\n  <div>\n    <label>Created By :</label>\n    <label>\n      <a href=\"mailto:{{createdByEmail}}\">{{createdByEmail}}</a>\n    </label>\n  </div>\n</div>","styles":[".audit-trail{background-color:#add8bb;min-height:100px;max-width:600px;padding:10px}.audit-trail div label{font-family:'Open Sans',sans-serif;font-size:14px;padding-top:5px;color:#000}.audit-trail div label:first-child{width:150px;font-weight:700;display:inline-table}.audit-trail div a{font-family:'Open Sans',sans-serif;font-size:14px;padding-top:5px}"]}]}],"members":{"lastModifiedByEmail":[{"__symbolic":"property","decorators":[{"__symbolic":"call","expression":{"__symbolic":"reference","module":"@angular/core","name":"Input","line":9,"character":3}}]}],"createdByEmail":[{"__symbolic":"property","decorators":[{"__symbolic":"call","expression":{"__symbolic":"reference","module":"@angular/core","name":"Input","line":10,"character":3}}]}],"created":[{"__symbolic":"property","decorators":[{"__symbolic":"call","expression":{"__symbolic":"reference","module":"@angular/core","name":"Input","line":11,"character":3}}]}],"lastModified":[{"__symbolic":"property","decorators":[{"__symbolic":"call","expression":{"__symbolic":"reference","module":"@angular/core","name":"Input","line":12,"character":3}}]}],"dateFormat":[{"__symbolic":"property","decorators":[{"__symbolic":"call","expression":{"__symbolic":"reference","module":"@angular/core","name":"Input","line":13,"character":3}}]}]}},"ɵg":{"__symbolic":"class","decorators":[{"__symbolic":"call","expression":{"__symbolic":"reference","module":"@angular/core","name":"Pipe","line":3,"character":1},"arguments":[{"name":"globaldatetime"}]}],"members":{"transform":[{"__symbolic":"method"}]}},"ɵh":{"__symbolic":"class","decorators":[{"__symbolic":"call","expression":{"__symbolic":"reference","module":"@angular/core","name":"Component","line":3,"character":1},"arguments":[{"selector":"sy-history-table","template":"<fieldset>\n  <legend>{{historyConfig.title}}</legend>\n  <table class=\"history-table\">\n    <thead>\n      <tr>\n        <th class=\"history-table-date-column\">\n          <div>{{historyConfig.dateHeaderText}}</div>\n        </th>\n        <th class=\"history-table-change-column history-text-container\">\n          <div>{{historyConfig.detailsHeaderText}}</div>\n          <div>\n            <button *ngIf=\"isExpand\" (click)=\"expand(isExpand)\" aria-label=\"expand more\">\n              <fa-icon [icon]=\"['fas', 'caret-up']\" size=\"2x\"></fa-icon>\n            </button>\n            <button *ngIf=\"!isExpand\" (click)=\"expand(isExpand)\" >\n              <fa-icon [icon]=\"['fas', 'caret-down']\" size=\"2x\"></fa-icon>\n              </button> \n           </div>\n        </th>\n      </tr>\n    </thead>\n    <tbody *ngIf=\"historyData?.length > 0\">\n      <tr *ngFor=\"let history of historyData\">\n        <td>\n          {{history.DateTimeChanged | globaldatetime}}\n        </td>\n        <td>\n          <div *ngIf=\"isExpand\" class=\"general-text\">\n            {{history.SummaryReason}}\n          </div>\n          <div *ngIf=\"!isExpand\" class=\"general-text\">\n            <div>{{history.DetailField}}</div>\n            <div>{{history.DetailOld}}</div>\n            <div>{{history.DetailNew}}</div>\n            <div>{{history.DetailChangedBy}}</div>\n          </div>\n        </td>\n      </tr>\n    </tbody>\n  </table>\n</fieldset>","styles":[".history-table tr td{text-align:left;border:1px solid #a69b97;padding:5px}.history-table tr th{text-align:left;border:1px solid #000;background-color:rgba(0,0,0,.65);padding:5px}.history-table thead tr th{text-align:left;min-height:20px;border:1px solid #a69b97;color:#fff;margin-right:5px}.history-table tr:nth-child(even){background-color:#efebe9;border:1px solid #a69b97}.history-table-date-column{min-width:100px;text-align:left}.history-table-change-column{min-width:300px;text-align:left}.history-table-change-column div{margin-top:8px}.history-table-change-column button{min-height:10px}fieldset{max-width:600px}table{border:2px solid #a69b97;border-collapse:collapse}button{background-color:transparent;border:none}fa-icon{color:#fff;text-align:left;margin:10px}.history-text-container{display:-webkit-box;display:flex;flex-wrap:wrap;text-align:center}.icon-end{text-align:end}"]}]}],"members":{"historyConfig":[{"__symbolic":"property","decorators":[{"__symbolic":"call","expression":{"__symbolic":"reference","module":"@angular/core","name":"Input","line":10,"character":3}}]}],"historyData":[{"__symbolic":"property","decorators":[{"__symbolic":"call","expression":{"__symbolic":"reference","module":"@angular/core","name":"Input","line":15,"character":3}}]}],"expand":[{"__symbolic":"method"}]}},"ɵi":{"__symbolic":"class","decorators":[{"__symbolic":"call","expression":{"__symbolic":"reference","module":"@angular/core","name":"Component","line":3,"character":1},"arguments":[{"selector":"sy-alert","template":"<div [ngClass]=\"[selectedType]\">\r\n  <div class=\"alert-container\">\r\n    <div class=\"alert-body\">\r\n      <fa-icon [icon]=\"selectedIcon\" size=\"lg\"></fa-icon>\r\n      <span class=\"alert-header\">{{title}}</span>\r\n      <span class=\"sr-only\">{{this.types[this.type]?.sr}}</span>\r\n      <span class=\"float-right\" *ngIf=\"showClose\" (click)=\"closeAlert()\" tabindex=\"0\" (keyup.enter)=\"closeAlert()\">\r\n        <fa-icon icon=\"times-circle\" size=\"1x\">\r\n        </fa-icon>\r\n      </span>\r\n    </div>\r\n    <div class=\"alert-body\">\r\n      <p *ngIf=\"description\">{{description}}</p>\r\n      <div *ngIf=\"descriptionList?.length > 0\">\r\n        <ul *ngFor=\"let desc of descriptionList\" type=\"disc\">\r\n          <li>{{desc}}</li>\r\n        </ul>\r\n      </div>\r\n      <ng-content select=\"[main-content]\"></ng-content>\r\n    </div>\r\n  </div>\r\n</div>","styles":["div{background:#fff}.float-right{float:right}.alert-body{padding:10px 5px}.alert-body fa-icon{margin-right:4px;margin-left:2px}.alert-error .alert-body,.alert-error .closeIcon{border-left:15px solid #ec1942!important}.alert-error .alert-body fa-icon,.alert-error .closeIcon fa-icon{color:#ec1942!important}.alert-error .alert-header{color:#ec1942}.alert-info .alert-body,.alert-info .closeIcon{border-left:10px solid #00a7cf}.alert-info .alert-body fa-icon,.alert-info .alert-header,.alert-info .closeIcon fa-icon{color:#00a7cf}.alert-success .alert-body,.alert-success .closeIcon{border-left:10px solid #4aa564}.alert-success .alert-body fa-icon,.alert-success .alert-header,.alert-success .closeIcon fa-icon{color:#4aa564}.alert-warning .alert-body,.alert-warning .closeIcon{border-left:10px solid #d84009}.alert-warning .alert-body fa-icon,.alert-warning .alert-header,.alert-warning .closeIcon fa-icon{color:#d84009}.alert-div{display:-webkit-box;display:flex;margin-bottom:15px;margin-top:15px;max-width:50em;font-size:16px}.alert-header{font-weight:600;font-size:20px;margin-bottom:5px;padding-left:5px}.alert-container{margin-bottom:15px;margin-top:15px;max-width:50em;font-size:16px;box-shadow:2px 1px 1px 1px rgba(85,84,84,.12)}"]}]}],"members":{"type":[{"__symbolic":"property","decorators":[{"__symbolic":"call","expression":{"__symbolic":"reference","module":"@angular/core","name":"Input","line":9,"character":3}}]}],"title":[{"__symbolic":"property","decorators":[{"__symbolic":"call","expression":{"__symbolic":"reference","module":"@angular/core","name":"Input","line":13,"character":3}}]}],"description":[{"__symbolic":"property","decorators":[{"__symbolic":"call","expression":{"__symbolic":"reference","module":"@angular/core","name":"Input","line":17,"character":3}}]}],"descriptionList":[{"__symbolic":"property","decorators":[{"__symbolic":"call","expression":{"__symbolic":"reference","module":"@angular/core","name":"Input","line":22,"character":3}}]}],"showClose":[{"__symbolic":"property","decorators":[{"__symbolic":"call","expression":{"__symbolic":"reference","module":"@angular/core","name":"Input","line":27,"character":3}}]}],"userMustDismiss":[{"__symbolic":"property","decorators":[{"__symbolic":"call","expression":{"__symbolic":"reference","module":"@angular/core","name":"Input","line":32,"character":3}}]}],"dismissTimer":[{"__symbolic":"property","decorators":[{"__symbolic":"call","expression":{"__symbolic":"reference","module":"@angular/core","name":"Input","line":37,"character":3}}]}],"dismiss":[{"__symbolic":"property","decorators":[{"__symbolic":"call","expression":{"__symbolic":"reference","module":"@angular/core","name":"Output","line":42,"character":3}}]}],"toggle":[{"__symbolic":"property","decorators":[{"__symbolic":"call","expression":{"__symbolic":"reference","module":"@angular/core","name":"Output","line":46,"character":3}}]}],"typeNotDefined":[{"__symbolic":"method"}],"closeAlert":[{"__symbolic":"method"}],"ngOnInit":[{"__symbolic":"method"}],"onDismissClick":[{"__symbolic":"method"}]}},"ɵj":{"__symbolic":"class","decorators":[{"__symbolic":"call","expression":{"__symbolic":"reference","module":"@angular/core","name":"Component","line":4,"character":1},"arguments":[{"selector":"sy-alert-footer","template":"<div class=\"alert-fixed-footer\">\r\n    <sy-alert *ngFor=\"let alert of alerts; let i = index\" [dismissTimer]=\"alert.timer\" [showClose]=\"true\" [userMustDismiss]=\"alert.mustDismiss ? alert.mustDismiss : false\" [type]=\"alert.type\" [title]=\"alert.title\" [description]=\"alert.description\" [descriptionList]=\"alert.descriptionList\"\r\n        (dismiss)=\"dismissFooterAlert(i)\">\r\n    </sy-alert>\r\n</div>","styles":[".alert-fixed-footer{min-width:300px;min-height:100px;position:absolute;z-index:1;bottom:0;right:0}"]}]}],"members":{"alerts":[{"__symbolic":"property","decorators":[{"__symbolic":"call","expression":{"__symbolic":"reference","module":"@angular/core","name":"Input","line":11,"character":3}}]}],"dismissAlert":[{"__symbolic":"property","decorators":[{"__symbolic":"call","expression":{"__symbolic":"reference","module":"@angular/core","name":"Output","line":12,"character":3}}]}],"__ctor__":[{"__symbolic":"constructor","parameters":[{"__symbolic":"reference","name":"ɵk"}]}],"ngOnInit":[{"__symbolic":"method"}],"dismissFooterAlert":[{"__symbolic":"method"}],"refreshAlerts":[{"__symbolic":"method"}]}},"ɵk":{"__symbolic":"class","decorators":[{"__symbolic":"call","expression":{"__symbolic":"reference","module":"@angular/core","name":"Injectable","line":2,"character":1}}],"members":{"getAlerts":[{"__symbolic":"method"}],"registerFooterAlert":[{"__symbolic":"method"}],"dismissFooterAlert":[{"__symbolic":"method"}]}},"ɵl":{"__symbolic":"class","decorators":[{"__symbolic":"call","expression":{"__symbolic":"reference","module":"@angular/core","name":"Component","line":3,"character":1},"arguments":[{"selector":"dos-header","template":"<div class=\"dos-header-toolbar\">\n    <div class=\"container clf-header\">\n        <div class=\"navbar-header\">\n            <a href=\"https://delaware.gov\">\n                <img src=\"https://gic.delaware.gov/wp-content/themes/dosgic_GIC_theme/img/delaware_global_d@2x.png\"\n                    alt=\"The Delaware.gov logo\" class=\"border_none delaware_d_logo\">\n            </a>\n            <a href=\"https://delaware.gov\">\n                <img src=\"https://gic.delaware.gov/wp-content/themes/dosgic_GIC_theme/img/delaware_global_text@2x.png\"\n                    alt=\"Delaware.gov - The Offical Website of the First State\" class=\"border_none delaware_text\">\n            </a>\n        </div>\n        <div class=\"masthead-nav\">\n            <ul>\n                <li>\n                    <a target=\"_blank\" href=\"http://delaware.gov/topics/agencylist_alpha\">\n                        <fa-icon [icon]=\"['far', 'building']\" size=\"lg\"></fa-icon>\n                        Agencies\n                    </a>\n                </li>\n                <li>\n                    <a target=\"_blank\" href=\"http://news.delaware.gov\">\n                        <fa-icon [icon]=\"['far', 'newspaper']\" size=\"lg\"></fa-icon>\n                        News\n                    </a>\n                </li>\n                <li>\n                    <a target=\"_blank\" href=\"http://delaware.gov/topics\">\n                        <fa-icon [icon]=\"['far', 'comments']\" size=\"lg\"></fa-icon>\n                        Topics\n                    </a>\n                </li>\n                <li>\n                    <a target=\"_blank\" href=\"http://delaware.gov/help/degov-contact.shtml\">\n                        <fa-icon [icon]=\"['fas', 'mobile-alt']\" size=\"lg\"></fa-icon>\n                        Contact\n                    </a>\n                </li>\n            </ul>\n        </div>\n    </div>\n</div>","styles":[".dos-header-toolbar{max-height:80px;background-color:#4bc1d2;min-height:80px;margin:0;width:100%}.navbar-header{padding-right:50px;margin-top:10px}.navbar-header a{margin-bottom:10px;color:transparent}fa-icon{color:#fff;width:1.25em;height:1em;display:inline-block;margin-right:8px}.clf-header{margin-left:15px;margin-bottom:1px;background-color:#4bc1d2;color:#fff;border-top:10px solid #4bc1d2;border-bottom:10px solid #4bc1d2}.delaware_d_logo{margin-left:0;width:40px;height:40px}.delaware_text{margin-top:5px;margin-left:0;width:160px;height:30px}img{border:0;vertical-align:middle;max-width:10rem;margin-right:5px}.masthead-nav{display:inline-block;text-align:center}.masthead-nav ul li a{color:#fff;font-size:16px;font-weight:700;font-family:\"Open Sans\",sans-serif!important;text-decoration:none;padding-bottom:15px;border-bottom:2px solid transparent;margin-right:20px;max-width:2rem}.masthead-nav>ul>li>a:hover{margin-bottom:10px;border-bottom:2px solid rgba(255,255,255,.25)}.title{margin-top:15px;padding-right:5px}.container{display:-webkit-box;display:flex;flex-wrap:wrap}ul{display:-webkit-box;display:flex;list-style:none}@media only screen and (min-device-width:320px) and (max-device-width:580px){.masthead-nav{display:none}}"]}]}],"members":{"__ctor__":[{"__symbolic":"constructor"}],"ngOnInit":[{"__symbolic":"method"}]}},"ɵm":{"__symbolic":"class","decorators":[{"__symbolic":"call","expression":{"__symbolic":"reference","module":"@angular/core","name":"Component","line":18,"character":1},"arguments":[{"selector":"sy-progress-bar","template":"<div class=\"progress\">\n    <div class=\"label\">{{ valueAsText }}</div>\n    <ng-container *ngTemplateOutlet=\"type === 'percent' ? percent : time\"></ng-container>\n  </div>\n  \n  <ng-template #percent>\n    <!-- Percent template -->\n    <div class=\"bar\">\n      <div class=\"fill animated\"\n        [style.width]=\"calculateBarFillPercentage()\"\n        role=\"progressbar\"\n        [attr.aria-valuenow]=\"value\"\n        [attr.aria-valuemin]=\"min\"\n        [attr.aria-valuemax]=\"max\"></div>\n    </div>\n  </ng-template>\n  \n  <ng-template #time>\n    <!-- Text value template -->\n    <div class=\"bar\">\n      <div class=\"fill animated\"\n        [style.width]=\"calculateBarFillPercentage()\"\n        role=\"progressbar\" \n        [attr.aria-valuenow]=\"value\"\n        [attr.aria-valuemin]=\"min\"\n        [attr.aria-valuemax]=\"max\"\n        [attr.aria-valuetext]=\"valueAsText\"></div>\n    </div>\n  </ng-template>","styles":[".bar .fill{height:1rem;border-radius:4px;background-color:#4bc1d2;box-shadow:0 0 1px 1px rgba(0,0,0,.25),inset 0 1px rgba(255,255,255,.1)}.bar .fill.animated{-webkit-transition:width .4s linear;transition:width .4s linear}"]}]}],"members":{"type":[{"__symbolic":"property","decorators":[{"__symbolic":"call","expression":{"__symbolic":"reference","module":"@angular/core","name":"Input","line":29,"character":3}}]}],"min":[{"__symbolic":"property","decorators":[{"__symbolic":"call","expression":{"__symbolic":"reference","module":"@angular/core","name":"Input","line":35,"character":3}}]}],"max":[{"__symbolic":"property","decorators":[{"__symbolic":"call","expression":{"__symbolic":"reference","module":"@angular/core","name":"Input","line":41,"character":3}}]}],"value":[{"__symbolic":"property","decorators":[{"__symbolic":"call","expression":{"__symbolic":"reference","module":"@angular/core","name":"Input","line":46,"character":3}}]}],"valueAsText":[{"__symbolic":"property","decorators":[{"__symbolic":"call","expression":{"__symbolic":"reference","module":"@angular/core","name":"Input","line":52,"character":3}}]}],"calculateBarFillPercentage":[{"__symbolic":"method"}]}},"ɵn":{"__symbolic":"class","decorators":[{"__symbolic":"call","expression":{"__symbolic":"reference","module":"@angular/core","name":"Component","line":9,"character":1},"arguments":[{"selector":"sy-action-button","template":"<button type=\"button\"\n        (click)=\"actionClicked()\"\n        [disabled]=\"disabled\"\n        class=\"usa-button action-button\">\n  <!-- <span [ngClass]=\"action?.icon\"></span>&nbsp; -->\n  <fa-icon [icon]=\"action?.icon\" size=\"1x\"></fa-icon>&nbsp;\n  {{ action?.label }}\n</button>\n","styles":[".action-button{margin-top:.5em;margin-right:.5em;margin-bottom:.5em;-webkit-appearance:none;-moz-appearance:none;appearance:none;background-color:#4bc1d2;border:0;border-radius:.1875rem;color:#fff;cursor:pointer;display:inline-block;font-family:'Open Sans',sans-serif;font-size:1rem;font-weight:700;line-height:1;outline:0;padding:1rem 2rem;text-align:center;text-decoration:none}"]}]}],"members":{"action":[{"__symbolic":"property","decorators":[{"__symbolic":"call","expression":{"__symbolic":"reference","module":"@angular/core","name":"Input","line":19,"character":3}}]}],"disabled":[{"__symbolic":"property","decorators":[{"__symbolic":"call","expression":{"__symbolic":"reference","module":"@angular/core","name":"Input","line":23,"character":3}}]}],"emitAction":[{"__symbolic":"property","decorators":[{"__symbolic":"call","expression":{"__symbolic":"reference","module":"@angular/core","name":"Output","line":27,"character":3}}]}],"emitCallback":[{"__symbolic":"property","decorators":[{"__symbolic":"call","expression":{"__symbolic":"reference","module":"@angular/core","name":"Output","line":31,"character":3}}]}],"actionClicked":[{"__symbolic":"method"}]}},"ɵo":{"__symbolic":"class","decorators":[{"__symbolic":"call","expression":{"__symbolic":"reference","module":"@angular/core","name":"Component","line":2,"character":1},"arguments":[{"selector":"sy-toolbar","template":"<div class=\"page\">\n  <div class=\"toolbar\">\n\n    <div class=\"toolbar-dropdown\">\n      <div class=\"toolbar-select\">\n        <a class=\"toolbar-toggle-button collapsed\" href=\"\">\n          <span>Collapse</span>\n        </a>\n      </div>\n    </div>\n\n    <div class=\"toolbar-expanded-content\">\n      <div class=\"accordion\">\n        <div class=\"accordion-header\">\n          <a href=\"\">Navigation</a>\n        </div>\n        <div class=\"accordion-content\">\n          <nav>\n            <ul class=\"usa-sidenav\">\n              <li class=\"usa-sidenav__item\">\n                <a href=\"\">Parent link</a>\n              </li>\n              <li class=\"usa-sidenav__item\">\n                <a href=\"\" class=\"usa-current\">Current page</a>\n                <ul class=\"usa-sidenav__sublist\">\n                  <li class=\"usa-sidenav__item\">\n                    <a href=\"\">Child link</a>\n                  </li>\n                  <li class=\"usa-sidenav__item\">\n                    <a href=\"\">Child link</a>\n                  </li>\n                  <li class=\"usa-sidenav__item\">\n                    <a href=\"\">Child link</a>\n                  </li>\n                  <li class=\"usa-sidenav__item\">\n                    <a href=\"\">Child link</a>\n                  </li>\n                  <li class=\"usa-sidenav__item\">\n                    <a href=\"\" class=\"usa-current\">Child link</a>\n                  </li>\n                </ul>\n              </li>\n              <li class=\"usa-sidenav__item\">\n                <a href=\"\">Parent link</a>\n              </li>\n            </ul>\n          </nav>\n        </div>\n      </div>\n      <div class=\"accordion\">\n        <div class=\"accordion-header\">\n          <a href=\"\">Filters</a>\n        </div>\n        <div class=\"accordion-content\">\n          <div class=\"filters\">\n            <div class=\"filter\">\n              <div class=\"filter-header\">\n                <a href=\"\">Service Classifications</a>\n              </div>\n              <div class=\"filter-content\">\n                <label class=\"usa-label\" for=\"input-type-naics\">NAICS</label>\n                <input class=\"usa-input\" id=\"input-type-naics\" name=\"input-type-naics\" type=\"text\">\n                <div class=\"selected-chips\">\n                  <span class=\"sam-tag sam-tag--chip\">\n                    111140 -- Wheat Farming\n                    <button class=\"sam-tag__close\">\n                      <span class=\"fas fa-times\" aria-hidden=\"true\"></span>\n                    </button>\n                  </span>\n                  <span class=\"sam-tag sam-tag--chip\">\n                    212222 -- Silver Ore Mining\n                    <button class=\"sam-tag__close\">\n                      <span class=\"fas fa-times\" aria-hidden=\"true\"></span>\n                    </button>\n                  </span>\n                  <span class=\"sam-tag sam-tag--chip\">\n                    541850 -- Outdoor Advertising\n                    <button class=\"sam-tag__close\">\n                      <span class=\"fas fa-times\" aria-hidden=\"true\"></span>\n                    </button>\n                  </span>\n                </div>\n                <label class=\"usa-label\" for=\"input-type-psc\">PSC</label>\n                <input class=\"usa-input\" id=\"input-type-psc\" name=\"input-type-psc\" type=\"text\">\n              </div>\n            </div>\n          </div>\n        </div>\n      </div>\n    </div>\n\n  </div>\n\n  <div class=\"page-content-header\">\n    Showing 1 to 10 of 21 registrations\n  </div>\n\n  <div class=\"page-content\">\n    <h3>Frontier Allied Partners, Inc</h3>\n    <p>\n      Lorem ipsum dolor sit amet, consectetur adipiscing elit. Cras laoreet faucibus arcu id bibendum. Mauris eleifend\n      massa purus, eu volutpat erat placerat egestas.\n    </p>\n  </div>\n</div>\n\n","styles":[".toolbar{display:inline-block;border:1px solid #fff;-webkit-transition:.2s ease-in-out;transition:.2s ease-in-out;-ms-grid-column:1;grid-column-start:1;-ms-grid-column-span:1;grid-column-end:2}.toolbar.expanded{border:1px solid #d8d8d8;width:300px;box-shadow:0 14px 24px 0 rgba(0,0,0,.06);border-radius:1px;-ms-grid-column-span:3;grid-column-end:3;-ms-grid-row:1;grid-row-start:1;-ms-grid-row-span:2;grid-row-end:3}.toolbar.expanded .toolbar-dropdown{padding:10px 15px}.toolbar-dropdown{position:relative;-webkit-transition:.2s ease-in-out;transition:.2s ease-in-out}.toolbar-select{background-color:#f7f9fa;border:1px solid #979797;padding:6px;border-radius:4px;width:45px;height:44px}.toolbar-toggle-button{background-color:#fff;display:block;width:31px;height:29px;border:1px solid #000;padding:5px;border-radius:3px;box-shadow:0 2px 8px 0 rgba(0,0,0,.29)}.toolbar-toggle-button span{position:absolute;left:-999em}.toolbar-toggle-button::before{content:'';display:block;background-color:#eff6fb;border:2px solid #112f4e;width:9px;-webkit-transition:.3s ease-in-out;transition:.3s ease-in-out}.toolbar-toggle-button:hover::before{background-color:#b7f5bd}.toolbar-toggle-button.collapsed::before{height:9px}.toolbar-toggle-button.expanded::before{height:18px}.toolbar-expanded-content{opacity:0;display:none;-webkit-transition:opacity .3s ease-in-out;transition:opacity .3s ease-in-out}.toolbar-expanded-content.open{opacity:1;display:block}.accordion{padding:12px 16px;border-top:1px solid #d8d8d8;border-bottom:1px solid #d8d8d8;border-left:1px solid #d8d8d8;border-right:1px solid #d8d8d8;background-color:#fff;margin-left:-1px;margin-right:-1px;margin-bottom:6px}.accordion.open{background-color:#eff6fb;box-shadow:inset 0 1px 7px 0 rgba(30,75,198,.16);border-left:1px solid #aac0d0;border-right:1px solid #aac0d0;border-color:#aac0d0;-webkit-transition:.2s ease-in;transition:.2s ease-in}.accordion-header a{font-size:16px;font-weight:600;color:#373737;text-decoration:none;-webkit-transition:.2s ease-in-out;transition:.2s ease-in-out}.accordion.open .accordion-header a{color:#0a3466}.accordion-content{display:none}.accordion.open .accordion-content{padding-top:10px;display:block}.page{margin:20px;display:-ms-grid;display:grid;-ms-grid-columns:80px 235px auto;grid-template-columns:80px 235px auto;-ms-grid-rows:46px auto;grid-template-rows:46px auto}.page-content-header{-ms-grid-column:2;grid-column-start:2;-ms-grid-column-span:-3;grid-column-end:-1;-ms-grid-row:1;grid-row-start:1;-ms-grid-row-span:1;grid-row-end:2;-ms-grid-row-align:center;align-self:center}.toolbar.expanded+.page-content-header{-ms-grid-column:3;grid-column-start:3}.page-content{-ms-grid-column:1;grid-column-start:1;-ms-grid-column-span:-2;grid-column-end:-1;-ms-grid-row:2;grid-row-start:2;-ms-grid-row-span:-3;grid-row-end:-1}.toolbar.expanded+.page-content-header+.page-content{-ms-grid-column:3;grid-column-start:3}.accordion-content nav{border:2px solid #d6d7d9;border-radius:0 6px 6px 0;background-color:#fff}.accordion-content nav .usa-sidenav{border-bottom:none}.filters .filter-header a{text-decoration:none;color:#323a45;font-weight:600}.filters .filter-content{display:none;background:#fff;box-shadow:inset 0 1px 3px 0 rgba(0,0,0,.5)}.filters .filter-content.open{display:-webkit-box;display:flex;-webkit-box-orient:vertical;-webkit-box-direction:normal;flex-direction:column;margin-top:12px;margin-left:-10px;margin-right:-10px;padding:0 10px 15px}.filters .filter-content .selected-chips{margin-top:5px}"]}]}],"members":{}},"ɵp":{"__symbolic":"class","decorators":[{"__symbolic":"call","expression":{"__symbolic":"reference","module":"@angular/core","name":"Component","line":11,"character":1},"arguments":[{"selector":"sy-export","template":"<div class=\"export-card\">\r\n    <div class=\"action-button\">\r\n        <button class=\"fileter-button\" [disabled]=\"isIpad\" (click)=\"exportAsExcelFile()\">\r\n            <fa-icon [icon]=\"['fas', 'file-export']\" size=\"lg\"></fa-icon>\r\n        </button>\r\n    </div>\r\n</div>\r\n<div id=\"container\" style=\"display:none;\"></div>","styles":[".export-card{padding:5px;margin:0 0 10px 10px;background:#fff;max-width:25rem}.unfiltered-icon{padding:1px;color:#4bc1d2;font-size:16px;border-radius:20px}.action-button button{margin-top:.5em;margin-right:1em;margin-bottom:.5em;-webkit-appearance:none;-moz-appearance:none;appearance:none;border-radius:.175rem;color:#fff;cursor:pointer;display:inline-block;font-family:'Open Sans',sans-serif;font-size:1rem;line-height:1;outline:0;padding:.5rem;text-align:center;text-decoration:none;border:2px solid teal}.unfileter-button{background-color:#fff}.fileter-button{background-color:#4bc1d2}"]}]}],"members":{"fileName":[{"__symbolic":"property","decorators":[{"__symbolic":"call","expression":{"__symbolic":"reference","module":"@angular/core","name":"Input","line":18,"character":5}}]}],"datasource":[{"__symbolic":"property","decorators":[{"__symbolic":"call","expression":{"__symbolic":"reference","module":"@angular/core","name":"Input","line":19,"character":5}}]}],"__ctor__":[{"__symbolic":"constructor","parameters":[{"__symbolic":"reference","module":"@angular/core","name":"Renderer2","line":22,"character":34}]}],"exportAsExcelFile":[{"__symbolic":"method"}]}},"ɵq":{"__symbolic":"class","decorators":[{"__symbolic":"call","expression":{"__symbolic":"reference","module":"@angular/core","name":"Component","line":2,"character":1},"arguments":[{"selector":"sy-required-message","template":"<div class=\"msg-container\">\n                <div class=\"label-align-right\">\n                <label>{{message}}</label>\n                </div>              \n            </div>","styles":["\n  .msg-container {\n    display: flex;\n    color: red;\n  }\n  .label-align-right {\n    flex:1;\n    text-align: right;\n   }\n  "]}]}],"members":{"message":[{"__symbolic":"property","decorators":[{"__symbolic":"call","expression":{"__symbolic":"reference","module":"@angular/core","name":"Input","line":23,"character":3}}]}]}},"ɵr":{"__symbolic":"class","decorators":[{"__symbolic":"call","expression":{"__symbolic":"reference","module":"@angular/core","name":"Component","line":7,"character":1},"arguments":[{"selector":"dos-footer","template":"<div id=\"footer\">\n    <div class=\"container\">\n        <h1 class=\"main_footer\">{{footerTitle}}</h1>\n        <hr>\n        <ng-container *ngTemplateOutlet=\"mainRowTemplate\"></ng-container>\n\n        <hr>\n        <div class=\"row\">\n            <ng-container *ngTemplateOutlet=\"socialMediaTemplate\"></ng-container>\n        </div>\n    </div>\n</div>\n\n<ng-template #mainRowTemplate>\n    <div class=\"row\">\n        <div class=\"content-container\">\n            <p *ngFor=\"let sec1 of footerSection1\">\n                <a href=\"sec1.path\">{{sec1.label}}</a>\n            </p>\n        </div>\n        <div class=\"content-container\">\n            <p *ngFor=\"let sec2 of footerSection2\">\n                <a href=\"sec2.path\">{{sec2.label}}</a>\n            </p>\n        </div>\n        <div class=\"content-container\">\n            <p *ngFor=\"let sec3 of footerSection3\">\n                <a href=\"sec3.path\">{{sec3.label}}</a>\n            </p>\n        </div>\n        <div class=\"content-container\">\n            <p *ngFor=\"let sec4 of footerSection4\">\n                <a *ngIf=\"!hasLogo\" href=\"sec4.path\">{{sec4.label}}</a>\n            </p>\n            <img *ngIf=\"hasLogo\" [src]=\"imageInfo.path\" [alt]=\"imageInfo.label\" class=\"hidden-xs img-responsive\">\n        </div>\n    </div>\n</ng-template>\n\n<ng-template #socialMediaTemplate>\n    <div class=\"social center-block\">\n        <div class=\"social_facebook\">\n            <a href=\"https://www.facebook.com/delaware.gov\" target=\"_blank\"><svg\n                    class=\"svg-inline--fa fa-facebook-square fa-w-14 fa-3x\" aria-hidden=\"true\" data-prefix=\"fab\"\n                    data-icon=\"facebook-square\" role=\"img\" xmlns=\"http://www.w3.org/2000/svg\" viewBox=\"0 0 448 512\"\n                    data-fa-i2svg=\"\">\n                    <path fill=\"currentColor\"\n                        d=\"M448 80v352c0 26.5-21.5 48-48 48h-85.3V302.8h60.6l8.7-67.6h-69.3V192c0-19.6 5.4-32.9 33.5-32.9H384V98.7c-6.2-.8-27.4-2.7-52.2-2.7-51.6 0-87 31.5-87 89.4v49.9H184v67.6h60.9V480H48c-26.5 0-48-21.5-48-48V80c0-26.5 21.5-48 48-48h352c26.5 0 48 21.5 48 48z\">\n                    </path>\n                </svg></a>\n        </div>\n        <div class=\"social_twitter\">\n            <a href=\"https://twitter.com/delaware_gov/\" target=\"_blank\"><svg\n                    class=\"svg-inline--fa fa-twitter-square fa-w-14 fa-3x\" aria-hidden=\"true\" data-prefix=\"fab\"\n                    data-icon=\"twitter-square\" role=\"img\" xmlns=\"http://www.w3.org/2000/svg\" viewBox=\"0 0 448 512\"\n                    data-fa-i2svg=\"\">\n                    <path fill=\"currentColor\"\n                        d=\"M400 32H48C21.5 32 0 53.5 0 80v352c0 26.5 21.5 48 48 48h352c26.5 0 48-21.5 48-48V80c0-26.5-21.5-48-48-48zm-48.9 158.8c.2 2.8.2 5.7.2 8.5 0 86.7-66 186.6-186.6 186.6-37.2 0-71.7-10.8-100.7-29.4 5.3.6 10.4.8 15.8.8 30.7 0 58.9-10.4 81.4-28-28.8-.6-53-19.5-61.3-45.5 10.1 1.5 19.2 1.5 29.6-1.2-30-6.1-52.5-32.5-52.5-64.4v-.8c8.7 4.9 18.9 7.9 29.6 8.3a65.447 65.447 0 0 1-29.2-54.6c0-12.2 3.2-23.4 8.9-33.1 32.3 39.8 80.8 65.8 135.2 68.6-9.3-44.5 24-80.6 64-80.6 18.9 0 35.9 7.9 47.9 20.7 14.8-2.8 29-8.3 41.6-15.8-4.9 15.2-15.2 28-28.8 36.1 13.2-1.4 26-5.1 37.8-10.2-8.9 13.1-20.1 24.7-32.9 34z\">\n                    </path>\n                </svg></a>\n        </div>\n        <div class=\"social_flickr\">\n            <a href=\"https://www.flickr.com/groups/delaware_gov/\" target=\"_blank\"><svg\n                    class=\"svg-inline--fa fa-flickr fa-w-14 fa-3x\" aria-hidden=\"true\" data-prefix=\"fab\"\n                    data-icon=\"flickr\" role=\"img\" xmlns=\"http://www.w3.org/2000/svg\" viewBox=\"0 0 448 512\"\n                    data-fa-i2svg=\"\">\n                    <path fill=\"currentColor\"\n                        d=\"M400 32H48C21.5 32 0 53.5 0 80v352c0 26.5 21.5 48 48 48h352c26.5 0 48-21.5 48-48V80c0-26.5-21.5-48-48-48zM144.5 319c-35.1 0-63.5-28.4-63.5-63.5s28.4-63.5 63.5-63.5 63.5 28.4 63.5 63.5-28.4 63.5-63.5 63.5zm159 0c-35.1 0-63.5-28.4-63.5-63.5s28.4-63.5 63.5-63.5 63.5 28.4 63.5 63.5-28.4 63.5-63.5 63.5z\">\n                    </path>\n                </svg></a>\n        </div>\n        <div class=\"social_youtube\">\n            <a href=\"https://www.youtube.com/user/DelawareGovernment\" target=\"_blank\"><svg\n                    class=\"svg-inline--fa fa-youtube-square fa-w-14 fa-3x\" aria-hidden=\"true\" data-prefix=\"fab\"\n                    data-icon=\"youtube-square\" role=\"img\" xmlns=\"http://www.w3.org/2000/svg\" viewBox=\"0 0 448 512\"\n                    data-fa-i2svg=\"\">\n                    <path fill=\"currentColor\"\n                        d=\"M186.8 202.1l95.2 54.1-95.2 54.1V202.1zM448 80v352c0 26.5-21.5 48-48 48H48c-26.5 0-48-21.5-48-48V80c0-26.5 21.5-48 48-48h352c26.5 0 48 21.5 48 48zm-42 176.3s0-59.6-7.6-88.2c-4.2-15.8-16.5-28.2-32.2-32.4C337.9 128 224 128 224 128s-113.9 0-142.2 7.7c-15.7 4.2-28 16.6-32.2 32.4-7.6 28.5-7.6 88.2-7.6 88.2s0 59.6 7.6 88.2c4.2 15.8 16.5 27.7 32.2 31.9C110.1 384 224 384 224 384s113.9 0 142.2-7.7c15.7-4.2 28-16.1 32.2-31.9 7.6-28.5 7.6-88.1 7.6-88.1z\">\n                    </path>\n                </svg></a>\n        </div>\n        <div class=\"social_rss\">\n            <a href=\"https://www.instagram.com/delaware_gov/\" target=\"_blank\"><svg\n                    class=\"svg-inline--fa fa-instagram fa-w-14 fa-3x\" aria-hidden=\"true\" data-prefix=\"fab\"\n                    data-icon=\"instagram\" role=\"img\" xmlns=\"http://www.w3.org/2000/svg\" viewBox=\"0 0 448 512\"\n                    data-fa-i2svg=\"\">\n                    <path fill=\"currentColor\"\n                        d=\"M224.1 141c-63.6 0-114.9 51.3-114.9 114.9s51.3 114.9 114.9 114.9S339 319.5 339 255.9 287.7 141 224.1 141zm0 189.6c-41.1 0-74.7-33.5-74.7-74.7s33.5-74.7 74.7-74.7 74.7 33.5 74.7 74.7-33.6 74.7-74.7 74.7zm146.4-194.3c0 14.9-12 26.8-26.8 26.8-14.9 0-26.8-12-26.8-26.8s12-26.8 26.8-26.8 26.8 12 26.8 26.8zm76.1 27.2c-1.7-35.9-9.9-67.7-36.2-93.9-26.2-26.2-58-34.4-93.9-36.2-37-2.1-147.9-2.1-184.9 0-35.8 1.7-67.6 9.9-93.9 36.1s-34.4 58-36.2 93.9c-2.1 37-2.1 147.9 0 184.9 1.7 35.9 9.9 67.7 36.2 93.9s58 34.4 93.9 36.2c37 2.1 147.9 2.1 184.9 0 35.9-1.7 67.7-9.9 93.9-36.2 26.2-26.2 34.4-58 36.2-93.9 2.1-37 2.1-147.8 0-184.8zM398.8 388c-7.8 19.6-22.9 34.7-42.6 42.6-29.5 11.7-99.5 9-132.1 9s-102.7 2.6-132.1-9c-19.6-7.8-34.7-22.9-42.6-42.6-11.7-29.5-9-99.5-9-132.1s-2.6-102.7 9-132.1c7.8-19.6 22.9-34.7 42.6-42.6 29.5-11.7 99.5-9 132.1-9s102.7-2.6 132.1 9c19.6 7.8 34.7 22.9 42.6 42.6 11.7 29.5 9 99.5 9 132.1s2.7 102.7-9 132.1z\">\n                    </path>\n                </svg></a>\n        </div>\n    </div>\n</ng-template>","styles":[".container{padding:15px;display:block;-webkit-box-flex:1;flex:1}.main_footer{font-family:\"Open Sans\",Helvetica,Arial,sans-serif;font-weight:500;color:#fff!important;font-size:40px;margin-top:20px}h1{color:#fff!important}hr{-moz-border-bottom-colors:none;-moz-border-left-colors:none;-moz-border-right-colors:none;-moz-border-top-colors:none;-webkit-border-image:none;-o-border-image:none;border-image:none;border:1px solid #fff;margin-bottom:20px;margin-top:20px;color:#fff;width:100%}p{color:#fff;display:block;margin:0;padding:0;-webkit-margin-start:0;margin-inline-start:0;-webkit-margin-end:0;margin-inline-end:0}#footer a,#footer a:link,#footer a:visited{text-decoration:none;color:#fff;-webkit-transition:.5s;transition:.5s;font-size:16px;font-family:\"Open Sans\",Helvetica,Arial,sans-serif}.row{margin-right:-15px;margin-left:-15px}.content-container{width:22%;float:left;position:relative;min-height:1px;padding-right:15px;padding-left:15px;padding-bottom:25px}div{display:block}.img-responsive>img{display:block;max-width:100%;height:auto}.pull-right{float:right!important}.col-lg-4{float:left;width:33.33333333%;position:relative;min-height:1px;padding-right:15px;padding-left:15px}#footer{background-color:#2d3032;font-size:15px;min-height:100%;clear:both;display:-webkit-box;display:flex;-webkit-box-flex:1;flex:1;line-height:1.5rem;max-height:40rem;width:100%;color:#fff}.social{max-width:500px;max-width:500px;display:block;margin-left:20px}.center-block{width:22%;margin-right:10px}.social_facebook{position:relative;height:50px;width:50px;margin:0 auto;display:inline-block}.social_facebook img{position:absolute;left:0;height:50px;width:50px;-webkit-transition:opacity .5s ease-in-out;transition:opacity .5s ease-in-out}.social_facebook img.top:hover{opacity:0;height:50px;width:50px}.social_twitter{position:relative;height:50px;width:50px;margin:0 auto;display:inline-block}.social_twitter img{position:absolute;left:0;height:50px;width:50px;-webkit-transition:opacity .5s ease-in-out;transition:opacity .5s ease-in-out}.social_twitter img.top:hover{opacity:0;height:50px;width:50px}.social_flickr{position:relative;height:50px;width:50px;margin:0 auto;display:inline-block}.social_flickr img{position:absolute;left:0;height:50px;width:50px;-webkit-transition:opacity .5s ease-in-out;transition:opacity .5s ease-in-out}.social_flickr img.top:hover{opacity:0;height:50px;width:50px}.social_youtube{position:relative;height:50px;width:50px;margin:0 auto;display:inline-block}.social_youtube img{position:absolute;left:0;height:50px;width:50px;-webkit-transition:opacity .5s ease-in-out;transition:opacity .5s ease-in-out}.social_youtube img.top:hover{opacity:0;height:50px;width:50px}.social_rss{position:relative;height:50px;width:50px;margin:0 auto;display:inline-block}.social_rss img{position:absolute;left:0;height:50px;width:50px;-webkit-transition:opacity .5s ease-in-out;transition:opacity .5s ease-in-out}.social_rss img.top:hover{opacity:0;height:50px;width:50px}.footer_logo{float:left;margin-right:5px;border:0;width:50px;height:50px}img{vertical-align:middle;border:0}@media (max-width:624px){.content-container{width:90%;float:none;align-content:center}.row{margin-left:15%;text-align:left}.main_footer{font-family:\"Open Sans\",Helvetica,Arial,sans-serif;font-weight:500;color:#fff!important;font-size:25px;margin-top:20px}.img-responsive>img{display:block;max-width:80%;height:auto;text-align:center;margin-left:-5%!important}#footer{max-height:100rem}}"]}]}],"members":{"footerTitle":[{"__symbolic":"property","decorators":[{"__symbolic":"call","expression":{"__symbolic":"reference","module":"@angular/core","name":"Input","line":14,"character":3}}]}],"footerSection1":[{"__symbolic":"property","decorators":[{"__symbolic":"call","expression":{"__symbolic":"reference","module":"@angular/core","name":"Input","line":16,"character":3}}]}],"footerSection4":[{"__symbolic":"property","decorators":[{"__symbolic":"call","expression":{"__symbolic":"reference","module":"@angular/core","name":"Input","line":59,"character":3}}]}],"imageInfo":[{"__symbolic":"property","decorators":[{"__symbolic":"call","expression":{"__symbolic":"reference","module":"@angular/core","name":"Input","line":60,"character":3}}]}],"hasLogo":[{"__symbolic":"property","decorators":[{"__symbolic":"call","expression":{"__symbolic":"reference","module":"@angular/core","name":"Input","line":66,"character":3}}]}],"footerSection3":[{"__symbolic":"property","decorators":[{"__symbolic":"call","expression":{"__symbolic":"reference","module":"@angular/core","name":"Input","line":67,"character":3}}]}],"footerSection2":[{"__symbolic":"property","decorators":[{"__symbolic":"call","expression":{"__symbolic":"reference","module":"@angular/core","name":"Input","line":111,"character":3}}]}]}},"ɵs":{"__symbolic":"class","decorators":[{"__symbolic":"call","expression":{"__symbolic":"reference","module":"@angular/core","name":"Component","line":4,"character":1},"arguments":[{"selector":"sy-download","animations":[{"__symbolic":"call","expression":{"__symbolic":"reference","module":"@angular/animations","name":"trigger","line":8,"character":4},"arguments":["accordion",[{"__symbolic":"call","expression":{"__symbolic":"reference","module":"@angular/animations","name":"state","line":9,"character":6},"arguments":["collapsed",{"__symbolic":"call","expression":{"__symbolic":"reference","module":"@angular/animations","name":"style","line":9,"character":25},"arguments":[{"height":"0px"}]}]},{"__symbolic":"call","expression":{"__symbolic":"reference","module":"@angular/animations","name":"state","line":12,"character":6},"arguments":["expanded",{"__symbolic":"call","expression":{"__symbolic":"reference","module":"@angular/animations","name":"style","line":12,"character":24},"arguments":[{"height":"*"}]}]},{"__symbolic":"call","expression":{"__symbolic":"reference","module":"@angular/animations","name":"transition","line":15,"character":6},"arguments":["collapsed => expanded",{"__symbolic":"call","expression":{"__symbolic":"reference","module":"@angular/animations","name":"animate","line":15,"character":42},"arguments":["100ms ease-in"]}]},{"__symbolic":"call","expression":{"__symbolic":"reference","module":"@angular/animations","name":"transition","line":16,"character":6},"arguments":["expanded => collapsed",{"__symbolic":"call","expression":{"__symbolic":"reference","module":"@angular/animations","name":"animate","line":16,"character":42},"arguments":["100ms ease-out"]}]}]]},{"__symbolic":"call","expression":{"__symbolic":"reference","module":"@angular/animations","name":"trigger","line":18,"character":4},"arguments":["intro",[{"__symbolic":"call","expression":{"__symbolic":"reference","module":"@angular/animations","name":"state","line":19,"character":6},"arguments":["fade",{"__symbolic":"call","expression":{"__symbolic":"reference","module":"@angular/animations","name":"style","line":19,"character":20},"arguments":[{"opacity":1,"transform":"translateY(0)"}]}]},{"__symbolic":"call","expression":{"__symbolic":"reference","module":"@angular/animations","name":"transition","line":23,"character":6},"arguments":["void => *",[{"__symbolic":"call","expression":{"__symbolic":"reference","module":"@angular/animations","name":"style","line":24,"character":8},"arguments":[{"opacity":0,"transform":"translateY(-30%)"}]},{"__symbolic":"call","expression":{"__symbolic":"reference","module":"@angular/animations","name":"animate","line":28,"character":8},"arguments":[".5s .5s cubic-bezier(0.175, 0.885, 0.320, 1.275)"]}]]},{"__symbolic":"call","expression":{"__symbolic":"reference","module":"@angular/animations","name":"transition","line":30,"character":6},"arguments":["* => void",[{"__symbolic":"call","expression":{"__symbolic":"reference","module":"@angular/animations","name":"animate","line":31,"character":8},"arguments":[".5s cubic-bezier(0.175, 0.885, 0.320, 1.275)",{"__symbolic":"call","expression":{"__symbolic":"reference","module":"@angular/animations","name":"style","line":31,"character":64},"arguments":[{"opacity":0,"transform":"translateY(-30%)"}]}]}]]}]]}],"template":"<section>\r\n  <div class=\"download-container-header\">\r\n    <h2>Packages</h2>\r\n    <ng-container *ngIf=\"packages\">\r\n      <span class=\"download-button\">\r\n        <a class=\"usa-button-small usa-button-gray\" *ngIf=\"hasPublicPackages() && downloadAllUrl\"\r\n          [attr.href]=\"downloadAllUrl\">\r\n          <!-- <span class=\"fa fa-cloud-download\" aria-hidden=\"true\"></span> -->\r\n          <fa-icon [icon]=\"['fas', 'cloud-download-alt']\" size=\"lg\"></fa-icon>\r\n          <span>Download All Packages</span>\r\n        </a>\r\n      </span>\r\n    </ng-container>\r\n  </div>\r\n\r\n  <ng-container *ngIf=\"packages && packages.length > 0\">\r\n    <div class=\"card download-container\" *ngFor=\"let package of packages\">\r\n      <!-- It's public -->\r\n      <div *ngIf=\"package.access.toLowerCase() === 'public'\" class=\"card-header {{ package.accordionState }}\"\r\n        (click)=\"toggleAccordion(package)\" tabindex=\"0\" (keyup.enter)=\"toggleAccordion(package)\">\r\n        <h3>{{ package.name }} ({{ package.resources?.length }})</h3>\r\n        <strong>Type: {{ package.type }}</strong>\r\n      </div>\r\n\r\n      <span *ngIf=\"package.access.toLowerCase() === 'public' && package.downloadUrl\" class=\"download-button\">\r\n        <a class=\"usa-button-small usa-button-gray\" [attr.href]=\"package.downloadUrl\">\r\n          <fa-icon [icon]=\"['fas', 'cloud-download-alt']\" size=\"lg\"></fa-icon>\r\n          <span>Download</span>\r\n        </a>\r\n      </span>\r\n\r\n      <ul *ngIf=\"package.access.toLowerCase() === 'public'\" [@accordion]=\"package.accordionState\"\r\n        class=\"usa-zebra-list\">\r\n        <li *ngFor=\"let resource of package.resources\">\r\n          <div class=\"download-info\">\r\n            <fa-icon [icon]=\"resource.typeInfo.iconClass\" size=\"1x\"></fa-icon>&nbsp;\r\n            <span class=\"download-info-icon\">\r\n              <span class=\"{{resource.typeInfo.iconClass}}\"></span>\r\n            </span>\r\n            <span class=\"download-info-link\">\r\n              <a [attr.href]=\"resource.downloadUrl\">\r\n                {{resource.description}}\r\n                <sup *ngIf=\"resource.size && resource.size != 0\">\r\n                  {{resource.size }}\r\n                </sup>\r\n              </a>\r\n            </span>\r\n            <span class=\"download-info-type\">\r\n              {{resource.typeInfo.name}}\r\n            </span>\r\n          </div>\r\n        </li>\r\n      </ul>\r\n\r\n      <!-- Its private -->\r\n      <div *ngIf=\"package.access.toLowerCase() === 'private'\" class=\"card-header-secure\">\r\n        <h3>{{ package.name }} ({{ package.resources?.length }})</h3>\r\n        <strong>Type: {{ package.type }}</strong>\r\n      </div>\r\n\r\n      <div *ngIf=\"package.access.toLowerCase() === 'private'\" class=\"card-secure-content\">\r\n        <p>\r\n          <fa-icon [icon]=\"['fas', 'lock']\" size=\"lg\"></fa-icon>\r\n          <em>Secure/sensitive attachments are not currently available, please go to <a\r\n              href=\"https://www.fbo.gov/\">FBO.gov</a> to view this attachment.</em>\r\n        </p>\r\n      </div>\r\n\r\n      <!-- Extra options -->\r\n      <div class=\"card-extra-content\">\r\n        <div class=\"label-container-inline\">\r\n          <fa-icon [icon]=\"['far', 'calendar-check']\" size=\"lg\"></fa-icon>\r\n\r\n          <strong>Posted on {{ package.postedDate }}</strong>\r\n        </div>\r\n        <div class=\"label-container-inline package-access\">\r\n          <fa-icon [icon]=\"['fas', 'unlock']\" size=\"lg\"></fa-icon>\r\n          <strong>{{isSecure(package.access)}}</strong>\r\n        </div>\r\n      </div>\r\n    </div>\r\n  </ng-container>\r\n\r\n  <div class=\"card\" *ngIf=\"packages.length < 1 && !attachmentError\">\r\n    <div class=\"card-secure-content usa-text-center\">\r\n      <fa-icon [icon]=\"['fas', 'spinner']\" size=\"lg\"></fa-icon>\r\n      <strong>Loading &hellip;</strong>\r\n    </div>\r\n  </div>\r\n\r\n  <div class=\"card\" *ngIf=\"packages.length < 1 && attachmentError\">\r\n    <div class=\"card-secure-content usa-text-center\">\r\n      <strong>No packages uploaded.</strong>\r\n    </div>\r\n  </div>\r\n</section>"}]}],"members":{"packages":[{"__symbolic":"property","decorators":[{"__symbolic":"call","expression":{"__symbolic":"reference","module":"@angular/core","name":"Input","line":43,"character":3}}]}],"attachmentError":[{"__symbolic":"property","decorators":[{"__symbolic":"call","expression":{"__symbolic":"reference","module":"@angular/core","name":"Input","line":47,"character":3}}]}],"downloadAllUrl":[{"__symbolic":"property","decorators":[{"__symbolic":"call","expression":{"__symbolic":"reference","module":"@angular/core","name":"Input","line":51,"character":3}}]}],"hasPublicPackages":[{"__symbolic":"method"}],"toggleAccordion":[{"__symbolic":"method"}],"isSecure":[{"__symbolic":"method"}]}},"ɵt":{"__symbolic":"class","decorators":[{"__symbolic":"call","expression":{"__symbolic":"reference","module":"@angular/core","name":"Component","line":3,"character":1},"arguments":[{"selector":"sy-poc","template":"<div class=\"sy-poc\">\r\n    <span class=\"sy-fullname\" *ngIf=\"data.fullName\">{{data.fullName}}<br></span>\r\n    <ng-container *ngIf=\"data.title\">{{data.title}}</ng-container>\r\n    <ng-container *ngIf=\"data.address\">{{data.address}}, <br></ng-container>\r\n    <ng-container *ngIf=\"data.address2\">{{data.address2}}<br /></ng-container>\r\n    <ng-container *ngIf=\"data.city || data.state || data.zip\">\r\n        <ng-container *ngIf=\"data.city\">{{data.city}}, </ng-container>\r\n        <ng-container *ngIf=\"data.state\">{{data.state}} </ng-container>\r\n        <ng-container *ngIf=\"data.zip\">{{data.zip}}</ng-container><br>\r\n    </ng-container>\r\n    <ng-container *ngIf=\"data.email\">\r\n        <fa-icon [icon]=\"['far', 'envelope']\" size=\"16px\"></fa-icon>\r\n        <a href=\"mailto:{{data.email}}\">{{data.email}}</a> <br>\r\n    </ng-container>\r\n    <ng-container *ngIf=\"data.phone\">\r\n        <fa-icon [icon]=\"['fas', 'phone']\" size=\"16px\"></fa-icon>\r\n\r\n        {{data.phone}}<br>\r\n    </ng-container>\r\n    <ng-container *ngIf=\"data.phone2\">\r\n        <fa-icon [icon]=\"['fas', 'phone']\" size=\"16px\"></fa-icon>\r\n        {{data.phone2}}<br>\r\n    </ng-container>\r\n    <ng-container *ngIf=\"data.fax\">\r\n        <fa-icon [icon]=\"['fas', 'fax']\" size=\"16px\"></fa-icon> {{data.fax}}<br>\r\n    </ng-container>\r\n    <ng-container *ngIf=\"data.website\">\r\n        <fa-icon [icon]=\"['fas', 'globe']\" size=\"16px\"></fa-icon>\r\n        {{data.website}}<br>\r\n    </ng-container>\r\n</div>","styles":[".sy-fullname{font-size:16px;font-weight:700;margin:0 5px 0 0}fa-icon{color:teal;margin-right:10px}.sy-poc{margin:10px}"]}]}],"members":{"data":[{"__symbolic":"property","decorators":[{"__symbolic":"call","expression":{"__symbolic":"reference","module":"@angular/core","name":"Input","line":13,"character":3}}]}]}},"ɵu":{"__symbolic":"class","decorators":[{"__symbolic":"call","expression":{"__symbolic":"reference","module":"@angular/core","name":"Component","line":2,"character":1},"arguments":[{"selector":"sy-copy-clipboard","template":"<div class=\"export-card\">\r\n    <div class=\"action-button\">\r\n        <button class=\"fileter-button\" (click)=\"copyToClipboard()\">\r\n            <fa-icon [icon]=\"['far', 'copy']\" size=\"lg\"></fa-icon>\r\n        </button>\r\n    </div>\r\n</div>\r\n<div id=\"container\" style=\"display:none;\"></div>","styles":[".export-card{padding:5px;margin:0 0 10px 10px;background:#fff;max-width:25rem}.unfiltered-icon{padding:1px;color:#4bc1d2;font-size:16px;border-radius:20px}.action-button button{margin-top:.5em;margin-right:1em;margin-bottom:.5em;-webkit-appearance:none;-moz-appearance:none;appearance:none;border-radius:.175rem;color:#fff;cursor:pointer;display:inline-block;font-family:'Open Sans',sans-serif;font-size:1rem;line-height:1;outline:0;padding:.5rem;text-align:center;text-decoration:none;border:2px solid teal}.unfileter-button{background-color:#fff}.fileter-button{background-color:#4bc1d2}"]}]}],"members":{"datasource":[{"__symbolic":"property","decorators":[{"__symbolic":"call","expression":{"__symbolic":"reference","module":"@angular/core","name":"Input","line":9,"character":5}}]}],"__ctor__":[{"__symbolic":"constructor","parameters":[{"__symbolic":"reference","module":"@angular/core","name":"Renderer2","line":14,"character":34}]}],"getText":[{"__symbolic":"method"}],"removeDuplicate":[{"__symbolic":"method"}],"copyToClipboard":[{"__symbolic":"method"}],"isUserAgentiOS":[{"__symbolic":"method"}],"selectText":[{"__symbolic":"method"}]}},"ɵv":{"__symbolic":"class","decorators":[{"__symbolic":"call","expression":{"__symbolic":"reference","module":"@angular/core","name":"Component","line":3,"character":1},"arguments":[{"selector":"sy-video-player","template":"<div class=\"video-container\">\r\n    <h3>{{videoConfig.title}}</h3>\r\n    <video width=\"490\" [poster]=\"videoConfig.poster\" crossorigin=\"anonymous\" controls [title]=\"videoConfig.title\"\r\n        #videoPly>\r\n        <source [src]=\"videoConfig.videoUrl\" type=\"video/mp4\" #videoSrc />\r\n        <track kind=\"captions\" label=\"English captions\" [src]=\"videoConfig.captionsUrl\" srclang=\"en\" default\r\n            #videoTrack />\r\n    </video>\r\n    <div class=\"video-description\">\r\n        <p> {{videoConfig.description}}</p>\r\n    </div>\r\n</div>","styles":[".video-description{max-width:450px;word-break:break-word;font-family:'Open Sans',sans-serif!important;font-size:16px}h3{color:#add8bb!important}.video-description a{font-size:12px}.video-container{width:450px;max-width:450px}"]}]}],"members":{"videoConfig":[{"__symbolic":"property","decorators":[{"__symbolic":"call","expression":{"__symbolic":"reference","module":"@angular/core","name":"Input","line":10,"character":5}}]}]}},"ɵw":{"__symbolic":"class","decorators":[{"__symbolic":"call","expression":{"__symbolic":"reference","module":"@angular/core","name":"NgModule","line":9,"character":1},"arguments":[{"declarations":[{"__symbolic":"reference","name":"ɵx"}],"exports":[{"__symbolic":"reference","name":"ɵx"}],"imports":[{"__symbolic":"reference","module":"@angular/common","name":"CommonModule","line":13,"character":4},{"__symbolic":"reference","name":"ɵy"},{"__symbolic":"reference","name":"ɵe"},{"__symbolic":"reference","name":"ɵba"},{"__symbolic":"reference","module":"@fortawesome/angular-fontawesome","name":"FontAwesomeModule","line":17,"character":4}]}]}],"members":{}},"ɵx":{"__symbolic":"class","decorators":[{"__symbolic":"call","expression":{"__symbolic":"reference","module":"@angular/core","name":"Component","line":71,"character":1},"arguments":[{"selector":"sy-upload","providers":[{"provide":{"__symbolic":"reference","module":"@angular/forms","name":"NG_VALUE_ACCESSOR","line":44,"character":11},"useExisting":{"__symbolic":"reference","name":"ɵx"},"multi":true}],"template":"<div class=\"sy-upload\">\r\n    <div class=\"file-container\" syDragDrop [disabled]=\"disabled\" (dropEvent)=\"onFilesChange($event)\" [dragState]=\"dragState\" (dragStateChange)=\"onDragStateChange($event)\" [ngClass]=\" { 'disabled': disabled, 'drag-border': shouldShowDropTarget }\" [ngStyle]=\"{'pointer-events': disabled ? 'none' : 'initial'}\">\r\n        <div class=\"file-container-no-drag\" *ngIf=\"!shouldShowDropTarget\">\r\n            <div class=\"text-center upload-cloud\" *ngIf=\"!anyFiles()\">\r\n                <fa-icon [icon]=\"['fas', 'cloud-upload-alt']\" size=\"2x\"></fa-icon>&nbsp;&nbsp;Drag and drop files here, or<a (click)=\"file.click()\">&nbsp;browse</a>\r\n            </div>\r\n            <div *ngFor=\"let uf of _model\" class=\"file-item\">\r\n                <div class=\"file-row\">\r\n                    <div class=\"file-name\">{{ uf.file.name }}</div>\r\n                    <div class=\"file-size\">{{ uf.file.size | filesize }}</div>\r\n                    <div class=\"file-delete\"><span class=\"icon close fa fa-times-circle\" (click)=\"onCloseClick(uf)\"></span></div>\r\n                </div>\r\n                <!-- <div class=\"file-progress\" *ngIf=\"shouldShowProgressBar(uf)\">\r\n                    <sy-progress-bar [value]=\"uf.upload.progress\"></sy-progress-bar>\r\n                </div> -->\r\n                <!-- <div class=\"file-error\" *ngIf=\"shouldShowError(uf)\">Error: {{uf.upload.error}}</div> -->\r\n            </div>\r\n            <div class=\"text-center\" *ngIf=\"anyFiles() && shouldAllowMoreFiles()\">\r\n                <fa-icon [icon]=\"['fas', 'cloud-upload-alt']\" size=\"2x\"></fa-icon>&nbsp;&nbsp;Drag and drop files here, or<a (click)=\"file.click()\">&nbsp;browse</a>\r\n            </div>\r\n        </div>\r\n        <div class=\"file-container-dragging text-center\" *ngIf=\"shouldShowDropTarget\">\r\n            Drop Files Here\r\n            <p class=\"text-center\"><span class=\"fa fa-cloud-upload\"></span></p>\r\n        </div>\r\n        <div *ngIf=\"showMaxFilesError\" class=\"file-max-error\">\r\n            <fa-icon [icon]=\"['fas', 'exclamation-triangle']\" size=\"2x\"></fa-icon>&nbsp;&nbsp;{{maxFilesErrorMessage()}}\r\n        </div>\r\n        <div *ngIf=\"!isAcceptableFileType && !shouldShowDropTarget\" class=\"file-max-error\">\r\n            <span> <fa-icon [icon]=\"['fas', 'exclamation-triangle']\" size=\"2x\"></fa-icon>&nbsp;&nbsp; Please select {{this.accept}} type of file.</span>\r\n        </div>\r\n\r\n        <!-- Hidden input to trigger the browser file selector -->\r\n        <input type=\"file\" #file [attr.id]=\"name\" [attr.accept]=\"accept\" ngModel class=\"hide\" (change)=\"onFilesChange($event)\" [attr.multiple]=\"maxFiles === 0 || maxFiles > 1 ? 'multiple' : null\">\r\n    </div>\r\n</div>","styles":[".sy-upload .icon.close{cursor:pointer;width:2rem;min-width:2rem;font-size:2rem;min-height:2rem;line-height:2rem}.sy-upload .hide{display:none}.sy-upload .disabled{pointer-events:none;cursor:not-allowed;opacity:.5}.sy-upload .file-container{max-width:46rem;border:1px solid #4f4f4f;padding:1rem}.sy-upload .upload-cloud{margin:3rem 0}.sy-upload .text-center a{color:#4bc1d2;font-weight:700;text-decoration:underline}.sy-upload .drag-border{border:3px dashed #9c9c9c;border-radius:1rem}.sy-upload .file-container-dragging{font-size:2.2rem;margin:1.5rem 0;color:#9c9c9c;pointer-events:none}.sy-upload .file-container-dragging *{pointer-events:none}.sy-upload .file-error{color:red}.sy-upload .file-max-error{background-color:#fffaf3;padding:1rem}.sy-upload .file-item{margin-bottom:.7em}.sy-upload .file-row{display:-webkit-box;display:flex;-webkit-box-pack:justify;justify-content:space-between}.sy-upload .file-row>:not(:first-child){padding-left:.5rem}.sy-upload .file-row .file-name{-webkit-box-flex:1;flex-grow:1;text-align:left;overflow-x:hidden;text-overflow:ellipsis;white-space:nowrap}.sy-upload .file-row .file-size{white-space:nowrap}.sy-upload .file-row .file-progress{width:8rem}.sy-upload .file-row .file-delete{min-width:2rem;text-align:center}.text-center{margin-top:0!important}.text-center a:hover{cursor:pointer}"]}]}],"members":{"uploadRequest":[{"__symbolic":"property","decorators":[{"__symbolic":"call","expression":{"__symbolic":"reference","module":"@angular/core","name":"Input","line":83,"character":3}}]}],"deleteRequest":[{"__symbolic":"property","decorators":[{"__symbolic":"call","expression":{"__symbolic":"reference","module":"@angular/core","name":"Input","line":90,"character":3}}]}],"maxFiles":[{"__symbolic":"property","decorators":[{"__symbolic":"call","expression":{"__symbolic":"reference","module":"@angular/core","name":"Input","line":96,"character":3}}]}],"uploadDeferred":[{"__symbolic":"property","decorators":[{"__symbolic":"call","expression":{"__symbolic":"reference","module":"@angular/core","name":"Input","line":101,"character":3}}]}],"accept":[{"__symbolic":"property","decorators":[{"__symbolic":"call","expression":{"__symbolic":"reference","module":"@angular/core","name":"Input","line":107,"character":3}}]}],"pattern":[{"__symbolic":"property","decorators":[{"__symbolic":"call","expression":{"__symbolic":"reference","module":"@angular/core","name":"Input","line":112,"character":3}}]}],"maxFileSizeInBytes":[{"__symbolic":"property","decorators":[{"__symbolic":"call","expression":{"__symbolic":"reference","module":"@angular/core","name":"Input","line":117,"character":3}}]}],"name":[{"__symbolic":"property","decorators":[{"__symbolic":"call","expression":{"__symbolic":"reference","module":"@angular/core","name":"Input","line":122,"character":3}}]}],"onModelFilesChanges":[{"__symbolic":"property","decorators":[{"__symbolic":"call","expression":{"__symbolic":"reference","module":"@angular/core","name":"Output","line":124,"character":3}}]}],"fileInput":[{"__symbolic":"property","decorators":[{"__symbolic":"call","expression":{"__symbolic":"reference","module":"@angular/core","name":"ViewChild","line":146,"character":3},"arguments":["file"]}]}],"__ctor__":[{"__symbolic":"constructor","parameters":[{"__symbolic":"reference","module":"@angular/common/http","name":"HttpClient","line":148,"character":34}]}],"onDragStateChange":[{"__symbolic":"method"}],"registerOnChange":[{"__symbolic":"method"}],"registerOnTouched":[{"__symbolic":"method"}],"setDisabledState":[{"__symbolic":"method"}],"writeValue":[{"__symbolic":"method"}],"onFilesChange":[{"__symbolic":"method"}],"startUpload":[{"__symbolic":"method"}],"validateFiles":[{"__symbolic":"method"}],"doUpload":[{"__symbolic":"method"}],"onCloseClick":[{"__symbolic":"method"}],"deleteFile":[{"__symbolic":"method"}],"removeFileFromList":[{"__symbolic":"method"}],"anyFiles":[{"__symbolic":"method"}],"shouldShowProgressBar":[{"__symbolic":"method"}],"shouldShowError":[{"__symbolic":"method"}],"shouldAllowMoreFiles":[{"__symbolic":"method"}],"emit":[{"__symbolic":"method"}],"maxFilesErrorMessage":[{"__symbolic":"method"}],"_numFilesValid":[{"__symbolic":"method"}],"_getDeleteRequestForFile":[{"__symbolic":"method"}],"_getHttpEventSteam":[{"__symbolic":"method"}],"_clearInput":[{"__symbolic":"method"}],"_checkAcceptableFileType":[{"__symbolic":"method"}]}},"ɵy":{"__symbolic":"class","decorators":[{"__symbolic":"call","expression":{"__symbolic":"reference","module":"@angular/core","name":"NgModule","line":5,"character":1},"arguments":[{"imports":[{"__symbolic":"reference","module":"@angular/common","name":"CommonModule","line":7,"character":4}],"declarations":[{"__symbolic":"reference","name":"ɵz"}],"exports":[{"__symbolic":"reference","name":"ɵz"}]}]}],"members":{}},"ɵz":{"__symbolic":"class","decorators":[{"__symbolic":"call","expression":{"__symbolic":"reference","module":"@angular/core","name":"Directive","line":14,"character":1},"arguments":[{"selector":"[syDragDrop]"}]}],"members":{"disabled":[{"__symbolic":"property","decorators":[{"__symbolic":"call","expression":{"__symbolic":"reference","module":"@angular/core","name":"Input","line":21,"character":5}}]}],"dragState":[{"__symbolic":"property","decorators":[{"__symbolic":"call","expression":{"__symbolic":"reference","module":"@angular/core","name":"Input","line":26,"character":5}}]}],"dragStateChange":[{"__symbolic":"property","decorators":[{"__symbolic":"call","expression":{"__symbolic":"reference","module":"@angular/core","name":"Output","line":30,"character":5}}]}],"dropEvent":[{"__symbolic":"property","decorators":[{"__symbolic":"call","expression":{"__symbolic":"reference","module":"@angular/core","name":"Output","line":34,"character":5}}]}],"__ctor__":[{"__symbolic":"constructor","parameters":[{"__symbolic":"reference","module":"@angular/core","name":"ElementRef","line":36,"character":37}]}],"_eventIsInTarget":[{"__symbolic":"method"}],"_eventHasFiles":[{"__symbolic":"method"}],"_eventIsInTargetWithFiles":[{"__symbolic":"method"}],"_updateDragState":[{"__symbolic":"method"}],"onElementDrop":[{"__symbolic":"method","decorators":[{"__symbolic":"call","expression":{"__symbolic":"reference","module":"@angular/core","name":"HostListener","line":58,"character":5},"arguments":["drop",["$event"]]}]}],"onElementDragOver":[{"__symbolic":"method","decorators":[{"__symbolic":"call","expression":{"__symbolic":"reference","module":"@angular/core","name":"HostListener","line":73,"character":5},"arguments":["dragover",["$event"]]}]}],"onElementDragend":[{"__symbolic":"method","decorators":[{"__symbolic":"call","expression":{"__symbolic":"reference","module":"@angular/core","name":"HostListener","line":87,"character":5},"arguments":["dragleave",["$event"]]}]}],"onWindowDragover":[{"__symbolic":"method","decorators":[{"__symbolic":"call","expression":{"__symbolic":"reference","module":"@angular/core","name":"HostListener","line":92,"character":5},"arguments":["window:dragover",["$event"]]}]}],"onWindowDrop":[{"__symbolic":"method","decorators":[{"__symbolic":"call","expression":{"__symbolic":"reference","module":"@angular/core","name":"HostListener","line":99,"character":5},"arguments":["window:drop",["$event"]]}]}],"_processFileEvent":[{"__symbolic":"method"}],"_processDragEvent":[{"__symbolic":"method"}]}},"ɵba":{"__symbolic":"class","decorators":[{"__symbolic":"call","expression":{"__symbolic":"reference","module":"@angular/core","name":"NgModule","line":4,"character":1},"arguments":[{"declarations":[{"__symbolic":"reference","name":"ɵbb"}],"exports":[{"__symbolic":"reference","name":"ɵbb"}],"imports":[{"__symbolic":"reference","module":"@angular/common","name":"CommonModule","line":8,"character":4}]}]}],"members":{}},"ɵbb":{"__symbolic":"class","decorators":[{"__symbolic":"call","expression":{"__symbolic":"reference","module":"@angular/core","name":"Pipe","line":3,"character":1},"arguments":[{"name":"filesize"}]}],"members":{"transform":[{"__symbolic":"method"}]}}},"origins":{"SyComponentsService":"./lib/sy-components.service","SyComponentsComponent":"./lib/sy-components.component","SyComponentsModule":"./lib/sy-components.module","ɵa":"./lib/history/history.component","ɵb":"./lib/listbox/listbox.component","ɵc":"./lib/wrappers/fieldset-wrapper/fieldset-wrapper.component","ɵd":"./lib/components/component.module","ɵe":"./lib/components/component.module","ɵf":"./lib/components/audit-trail/audit-trail.component","ɵg":"./lib/globaldatetime.pipe","ɵh":"./lib/components/history-table/history-table.component","ɵi":"./lib/components/alert/alert.component","ɵj":"./lib/components/alert-footer/alert-footer.component","ɵk":"./lib/components/alert-footer/alert-footer.service","ɵl":"./lib/components/dos-header/dos-header.component","ɵm":"./lib/components/progress-bar/progress-bar.component","ɵn":"./lib/components/action-button/action-button.component","ɵo":"./lib/components/toolbar/toolbar.component","ɵp":"./lib/components/export/export.component","ɵq":"./lib/components/required-message/required-message.component","ɵr":"./lib/components/dos-footer/dos-footer.component","ɵs":"./lib/components/download/download.component","ɵt":"./lib/components/point-of-contact/point-of-contact.component","ɵu":"./lib/components/copy-to-clipboard/copy-clipboard.component","ɵv":"./lib/components/video/video.component","ɵw":"./lib/upload/upload.module","ɵx":"./lib/upload/upload.component","ɵy":"./lib/directives/directive.module","ɵz":"./lib/directives/drag-drop/drag-drop.directive","ɵba":"./lib/pipes/pipes.module","ɵbb":"./lib/pipes/file-size/file-size.pipe"},"importAs":"sy-components"}